{
  "_id": "7SUMfxLZfEpyTxUg",
  "name": "G10 Blueprint Level Six",
  "flags": {
    "core": {}
  },
  "pages": [
    {
      "name": "G10 Blueprint Level Six",
      "type": "image",
      "src": "modules/footsteps-and-maps/artwork/npc-maps/D10-av-blueprint-level06.webp",
      "title": {
        "show": false,
        "level": 1
      },
      "_id": "dfzpFPepzNRQwr9g",
      "image": {},
      "text": {
        "format": 1
      },
      "video": {
        "controls": true,
        "volume": 0.5
      },
      "system": {},
      "sort": 0,
      "ownership": {
        "default": -1
      },
      "flags": {},
      "_stats": {
        "coreVersion": "13.351",
        "systemId": null,
        "systemVersion": null,
        "createdTime": null,
        "modifiedTime": null,
        "lastModifiedBy": null,
        "compendiumSource": null,
        "duplicateSource": null,
        "exportSource": null
      },
      "category": null,
      "_key": "!journal.pages!7SUMfxLZfEpyTxUg.dfzpFPepzNRQwr9g"
    }
  ],
  "ownership": {
    "default": 0,
    "1H5XKXyphHEmdKWt": 3
  },
  "_stats": {
    "systemId": "pf2e",
    "systemVersion": "4.4.2",
    "coreVersion": "13.351",
    "createdTime": 1670773784174,
    "modifiedTime": 1773935176284,
    "lastModifiedBy": "t3zbQ4JmS5HX3GXP",
    "compendiumSource": "Compendium.footsteps-and-maps.footsteps-and-maps-journals.7SUMfxLZfEpyTxUg",
    "duplicateSource": null,
    "exportSource": null
  },
  "folder": null,
  "sort": 600000,
  "categories": [],
  "_key": "!journal!7SUMfxLZfEpyTxUg"
}
